<?xml version="1.0" encoding="UTF-8"?>
<objects serializationModel="Studio.01.10.00">
    <object class="Event" id="{12fc479b-7eaf-4518-9338-df7df009d295}">
        <property name="name">
            <value>play_RunningWoodFloorboards</value>
        </property>
        <property name="outputFormat">
            <value>1</value>
        </property>
        <relationship name="folder">
            <destination>{f81ad469-5520-4c3f-99f4-2deff97af566}</destination>
        </relationship>
        <relationship name="mixer">
            <destination>{ca0b0007-f4fc-43a8-a848-c8d9b697d793}</destination>
        </relationship>
        <relationship name="masterTrack">
            <destination>{cf630753-0131-4052-a8aa-7e0617b8e766}</destination>
        </relationship>
        <relationship name="mixerInput">
            <destination>{e5bddaf5-a608-47c4-9231-d1aa7f59ec80}</destination>
        </relationship>
        <relationship name="automatableProperties">
            <destination>{ad01a847-f50f-49e8-ba5d-7b34487c0b7d}</destination>
        </relationship>
        <relationship name="markerTracks">
            <destination>{61615ec9-a140-4196-a2d6-74e3f8069926}</destination>
        </relationship>
        <relationship name="groupTracks">
            <destination>{b96177c6-be4f-4857-b9fe-93da9e0f3191}</destination>
            <destination>{788230cc-5050-4937-881f-f3a92ef8ab2e}</destination>
            <destination>{20a096fd-1e6e-4d09-995f-d37be893efff}</destination>
        </relationship>
        <relationship name="timeline">
            <destination>{270f277d-2fe4-4dc7-8c2f-a6a1fe179d8a}</destination>
        </relationship>
        <relationship name="banks">
            <destination>{951dab84-5c30-4164-a814-a603c1258ce1}</destination>
        </relationship>
    </object>
    <object class="EventMixer" id="{ca0b0007-f4fc-43a8-a848-c8d9b697d793}">
        <relationship name="masterBus">
            <destination>{fd4651dc-a717-46e1-98cb-2a9dfd898b64}</destination>
        </relationship>
    </object>
    <object class="MasterTrack" id="{cf630753-0131-4052-a8aa-7e0617b8e766}">
        <relationship name="mixerGroup">
            <destination>{fd4651dc-a717-46e1-98cb-2a9dfd898b64}</destination>
        </relationship>
    </object>
    <object class="MixerInput" id="{e5bddaf5-a608-47c4-9231-d1aa7f59ec80}">
        <relationship name="effectChain">
            <destination>{40f1b1d6-5c03-4e9f-b88f-6e197b9768b2}</destination>
        </relationship>
        <relationship name="panner">
            <destination>{63fd5195-cbb2-4218-a938-a46e0f3385fc}</destination>
        </relationship>
        <relationship name="output">
            <destination>{97d50c25-5af9-4fde-99bf-094c1a38ac1a}</destination>
        </relationship>
    </object>
    <object class="EventAutomatableProperties" id="{ad01a847-f50f-49e8-ba5d-7b34487c0b7d}"/>
    <object class="MarkerTrack" id="{61615ec9-a140-4196-a2d6-74e3f8069926}"/>
    <object class="GroupTrack" id="{b96177c6-be4f-4857-b9fe-93da9e0f3191}">
        <relationship name="modules">
            <destination>{0aa8b1ea-22f5-4a45-9c5e-b2eb0bf30e11}</destination>
        </relationship>
        <relationship name="mixerGroup">
            <destination>{01a458df-3215-4b4c-9e37-1e322b12480c}</destination>
        </relationship>
    </object>
    <object class="GroupTrack" id="{788230cc-5050-4937-881f-f3a92ef8ab2e}">
        <relationship name="modules">
            <destination>{6cc43af2-b3ec-46e9-975a-d485868aa5b8}</destination>
        </relationship>
        <relationship name="mixerGroup">
            <destination>{b58965da-9914-46b8-82bb-a2918a1afe54}</destination>
        </relationship>
    </object>
    <object class="GroupTrack" id="{20a096fd-1e6e-4d09-995f-d37be893efff}">
        <relationship name="modules">
            <destination>{a3e91002-24db-4397-bf74-45f04f60af0d}</destination>
        </relationship>
        <relationship name="mixerGroup">
            <destination>{a24dd91a-9232-4f74-989e-037b28b691ed}</destination>
        </relationship>
    </object>
    <object class="Timeline" id="{270f277d-2fe4-4dc7-8c2f-a6a1fe179d8a}">
        <relationship name="modules">
            <destination>{a3e91002-24db-4397-bf74-45f04f60af0d}</destination>
            <destination>{6cc43af2-b3ec-46e9-975a-d485868aa5b8}</destination>
            <destination>{0aa8b1ea-22f5-4a45-9c5e-b2eb0bf30e11}</destination>
        </relationship>
    </object>
    <object class="EventMixerMaster" id="{fd4651dc-a717-46e1-98cb-2a9dfd898b64}">
        <relationship name="effectChain">
            <destination>{ca10c788-51b5-4ed7-9df1-8983ffefe1ab}</destination>
        </relationship>
        <relationship name="panner">
            <destination>{820a5cbc-5e22-4576-b555-d1e9cac85a91}</destination>
        </relationship>
        <relationship name="mixer">
            <destination>{ca0b0007-f4fc-43a8-a848-c8d9b697d793}</destination>
        </relationship>
    </object>
    <object class="MixerBusEffectChain" id="{40f1b1d6-5c03-4e9f-b88f-6e197b9768b2}">
        <relationship name="effects">
            <destination>{fe116f0e-e6b6-47c9-b144-db2d57a8dc8e}</destination>
        </relationship>
    </object>
    <object class="MixerBusPanner" id="{63fd5195-cbb2-4218-a938-a46e0f3385fc}"/>
    <object class="MultiSound" id="{0aa8b1ea-22f5-4a45-9c5e-b2eb0bf30e11}">
        <property name="length">
            <value>0.25</value>
        </property>
        <property name="pitch">
            <value>0.800000012</value>
        </property>
        <relationship name="modulators">
            <destination>{949b7f0a-8415-4fb6-b759-6918f3944343}</destination>
            <destination>{5b383c55-900e-4d9c-8358-d36154188f50}</destination>
        </relationship>
        <relationship name="fadeOutCurve">
            <destination>{6374d763-1f00-4cfc-9731-de69b7160c46}</destination>
        </relationship>
        <relationship name="sounds">
            <destination>{8c68cf6f-fd30-4dce-9da2-9f999fc78259}</destination>
            <destination>{e1a4dafb-8f55-40c9-bf25-53cb0fec8dac}</destination>
            <destination>{2a61c14b-9675-4c00-8d0f-9a3314f7ddac}</destination>
            <destination>{499aa1c8-dcbc-4231-8622-dd8b1c77a5cb}</destination>
            <destination>{93339963-2e69-453e-9887-5c43bcc6e113}</destination>
            <destination>{c7863556-5798-4d93-a0e2-5004e2b7926f}</destination>
        </relationship>
    </object>
    <object class="EventMixerGroup" id="{01a458df-3215-4b4c-9e37-1e322b12480c}">
        <property name="volume">
            <value>4</value>
        </property>
        <property name="name">
            <value>Footsteps</value>
        </property>
        <relationship name="effectChain">
            <destination>{9b4a3d32-9c4e-479b-aca8-f67227407bcc}</destination>
        </relationship>
        <relationship name="panner">
            <destination>{553e7df2-d057-44c5-8b5e-4d292a8b8c51}</destination>
        </relationship>
        <relationship name="output">
            <destination>{fd4651dc-a717-46e1-98cb-2a9dfd898b64}</destination>
        </relationship>
    </object>
    <object class="MultiSound" id="{6cc43af2-b3ec-46e9-975a-d485868aa5b8}">
        <property name="triggerProbabilityEnabled">
            <value>true</value>
        </property>
        <property name="triggerProbability">
            <value>20.5</value>
        </property>
        <property name="length">
            <value>0.25</value>
        </property>
        <property name="delayType">
            <value>0</value>
        </property>
        <property name="maximumTimeDelay">
            <value>100</value>
        </property>
        <property name="pitch">
            <value>0.800000012</value>
        </property>
        <relationship name="modulators">
            <destination>{b80d345c-bdc3-4697-b5db-deab1f1798f5}</destination>
            <destination>{cf26ddce-869f-404b-a28d-4b549fd706d7}</destination>
        </relationship>
        <relationship name="fadeOutCurve">
            <destination>{e1679d93-9345-456e-9208-b65b35b53a32}</destination>
        </relationship>
        <relationship name="sounds">
            <destination>{b18bfddb-3ac2-4244-baa0-a13584b3c38d}</destination>
            <destination>{84c7e78c-c556-469a-b42f-a316eb3448d1}</destination>
            <destination>{7f631a9c-f9e4-4390-8ab3-0c88e15b6bc0}</destination>
        </relationship>
    </object>
    <object class="EventMixerGroup" id="{b58965da-9914-46b8-82bb-a2918a1afe54}">
        <property name="volume">
            <value>-4.5</value>
        </property>
        <property name="name">
            <value>Creaking</value>
        </property>
        <relationship name="effectChain">
            <destination>{c61b4773-bec5-4f9d-8b5d-539de50b3a79}</destination>
        </relationship>
        <relationship name="panner">
            <destination>{30c878cd-fd89-45da-a772-baee86ef4563}</destination>
        </relationship>
        <relationship name="output">
            <destination>{fd4651dc-a717-46e1-98cb-2a9dfd898b64}</destination>
        </relationship>
    </object>
    <object class="MultiSound" id="{a3e91002-24db-4397-bf74-45f04f60af0d}">
        <property name="length">
            <value>0.25</value>
        </property>
        <property name="delayType">
            <value>0</value>
        </property>
        <property name="minimumTimeDelay">
            <value>100</value>
        </property>
        <property name="maximumTimeDelay">
            <value>200</value>
        </property>
        <relationship name="modulators">
            <destination>{7ec3a618-4274-4a3e-bf63-7f8ff9b5e50d}</destination>
        </relationship>
        <relationship name="fadeOutCurve">
            <destination>{d22e9efc-5c5d-41e1-b4bb-2f6324e408e3}</destination>
        </relationship>
        <relationship name="sounds">
            <destination>{42d6c30a-3d6c-445b-bd15-9820996034ff}</destination>
            <destination>{4673d664-ecba-4e30-bbe2-3f0326f4b970}</destination>
            <destination>{69efb098-63ce-4b37-853c-56c8f463a86e}</destination>
            <destination>{89ade613-8122-4b41-93d3-8a3db4c9841a}</destination>
            <destination>{d3a7cbd3-d24e-4fd6-baa2-ab69f6869696}</destination>
            <destination>{c39a76be-d22d-432c-bbe4-99c039efa272}</destination>
        </relationship>
    </object>
    <object class="EventMixerGroup" id="{a24dd91a-9232-4f74-989e-037b28b691ed}">
        <property name="volume">
            <value>-24.5</value>
        </property>
        <property name="name">
            <value>EquipmentJingle</value>
        </property>
        <relationship name="effectChain">
            <destination>{85413641-f77c-4e35-b620-5b1eec9f96e1}</destination>
        </relationship>
        <relationship name="panner">
            <destination>{3e19807b-630e-49a9-a46b-f7a0a9edd452}</destination>
        </relationship>
        <relationship name="output">
            <destination>{fd4651dc-a717-46e1-98cb-2a9dfd898b64}</destination>
        </relationship>
    </object>
    <object class="MixerBusEffectChain" id="{ca10c788-51b5-4ed7-9df1-8983ffefe1ab}">
        <relationship name="effects">
            <destination>{0bdff22d-2f0a-4354-927a-663962f5b41e}</destination>
            <destination>{4bab4876-a235-4b22-a8b0-e8c0fc485a1e}</destination>
            <destination>{9d366cb7-e669-4b78-ae1e-1fdc874a5865}</destination>
        </relationship>
    </object>
    <object class="MixerBusPanner" id="{820a5cbc-5e22-4576-b555-d1e9cac85a91}">
        <property name="surroundPanDirection">
            <value>-135</value>
        </property>
    </object>
    <object class="MixerBusFader" id="{fe116f0e-e6b6-47c9-b144-db2d57a8dc8e}"/>
    <object class="RandomizerModulator" id="{949b7f0a-8415-4fb6-b759-6918f3944343}">
        <property name="nameOfPropertyBeingModulated">
            <value>volume</value>
        </property>
        <property name="amount">
            <value>3.5</value>
        </property>
    </object>
    <object class="RandomizerModulator" id="{5b383c55-900e-4d9c-8358-d36154188f50}">
        <property name="nameOfPropertyBeingModulated">
            <value>pitch</value>
        </property>
        <property name="amount">
            <value>6</value>
        </property>
    </object>
    <object class="FadeCurve" id="{6374d763-1f00-4cfc-9731-de69b7160c46}">
        <relationship name="startPoint">
            <destination>{fc7271c3-bc1f-4677-b1e2-23b6211487ad}</destination>
        </relationship>
        <relationship name="endPoint">
            <destination>{2d04ce69-498e-4cc3-aca5-a7c850072134}</destination>
        </relationship>
    </object>
    <object class="SingleSound" id="{8c68cf6f-fd30-4dce-9da2-9f999fc78259}">
        <relationship name="audioFile">
            <destination>{0175926c-a254-43b4-84fd-64c31cc9c9e8}</destination>
        </relationship>
    </object>
    <object class="SingleSound" id="{e1a4dafb-8f55-40c9-bf25-53cb0fec8dac}">
        <relationship name="audioFile">
            <destination>{30cdd1f5-3e5b-44f5-ba9c-55b317f92e46}</destination>
        </relationship>
    </object>
    <object class="SingleSound" id="{2a61c14b-9675-4c00-8d0f-9a3314f7ddac}">
        <relationship name="audioFile">
            <destination>{7dab0069-597d-4676-b9bc-ddd6ad097bbe}</destination>
        </relationship>
    </object>
    <object class="SingleSound" id="{499aa1c8-dcbc-4231-8622-dd8b1c77a5cb}">
        <relationship name="audioFile">
            <destination>{585b9dbe-92e5-4328-a970-d8fd4484f3d7}</destination>
        </relationship>
    </object>
    <object class="SingleSound" id="{93339963-2e69-453e-9887-5c43bcc6e113}">
        <relationship name="audioFile">
            <destination>{1a9670f6-d070-4fc4-91ae-524549d6b003}</destination>
        </relationship>
    </object>
    <object class="SingleSound" id="{c7863556-5798-4d93-a0e2-5004e2b7926f}">
        <relationship name="audioFile">
            <destination>{58b10b50-5c63-4ee3-9790-7b19db8a0a85}</destination>
        </relationship>
    </object>
    <object class="MixerBusEffectChain" id="{9b4a3d32-9c4e-479b-aca8-f67227407bcc}">
        <relationship name="effects">
            <destination>{3b26159c-47fa-4ce9-ad2a-45317fa9c99a}</destination>
            <destination>{c3f7ee8e-83bf-4a91-835e-635929336d03}</destination>
        </relationship>
    </object>
    <object class="MixerBusPanner" id="{553e7df2-d057-44c5-8b5e-4d292a8b8c51}"/>
    <object class="RandomizerModulator" id="{b80d345c-bdc3-4697-b5db-deab1f1798f5}">
        <property name="nameOfPropertyBeingModulated">
            <value>volume</value>
        </property>
        <property name="amount">
            <value>4.5</value>
        </property>
    </object>
    <object class="RandomizerModulator" id="{cf26ddce-869f-404b-a28d-4b549fd706d7}">
        <property name="nameOfPropertyBeingModulated">
            <value>pitch</value>
        </property>
        <property name="amount">
            <value>4</value>
        </property>
    </object>
    <object class="FadeCurve" id="{e1679d93-9345-456e-9208-b65b35b53a32}">
        <relationship name="startPoint">
            <destination>{807a6d04-d186-4b28-8f14-5249636e9751}</destination>
        </relationship>
        <relationship name="endPoint">
            <destination>{c882bda8-7808-45c0-84c4-b8dd8df3cabe}</destination>
        </relationship>
    </object>
    <object class="SingleSound" id="{b18bfddb-3ac2-4244-baa0-a13584b3c38d}">
        <relationship name="audioFile">
            <destination>{9f5ac4b8-bd69-4679-a913-db943336ca85}</destination>
        </relationship>
    </object>
    <object class="SingleSound" id="{84c7e78c-c556-469a-b42f-a316eb3448d1}">
        <relationship name="audioFile">
            <destination>{2ef778f0-9e1a-4e0a-83af-4c6a3d3f5574}</destination>
        </relationship>
    </object>
    <object class="SingleSound" id="{7f631a9c-f9e4-4390-8ab3-0c88e15b6bc0}">
        <relationship name="audioFile">
            <destination>{b478d501-6cfb-41d2-bb22-ce7df996eb46}</destination>
        </relationship>
    </object>
    <object class="MixerBusEffectChain" id="{c61b4773-bec5-4f9d-8b5d-539de50b3a79}">
        <relationship name="effects">
            <destination>{d15e0b0f-fb67-4133-9299-1b0cacd72cf2}</destination>
            <destination>{057edcb0-847b-4dfc-a184-2192750a60ba}</destination>
        </relationship>
    </object>
    <object class="MixerBusPanner" id="{30c878cd-fd89-45da-a772-baee86ef4563}"/>
    <object class="RandomizerModulator" id="{7ec3a618-4274-4a3e-bf63-7f8ff9b5e50d}">
        <property name="nameOfPropertyBeingModulated">
            <value>volume</value>
        </property>
        <property name="amount">
            <value>3</value>
        </property>
    </object>
    <object class="FadeCurve" id="{d22e9efc-5c5d-41e1-b4bb-2f6324e408e3}">
        <relationship name="startPoint">
            <destination>{59f60288-e278-4545-a888-ad0bf239b22f}</destination>
        </relationship>
        <relationship name="endPoint">
            <destination>{fd28e063-9a64-4303-89f7-3fef0115f372}</destination>
        </relationship>
    </object>
    <object class="SingleSound" id="{42d6c30a-3d6c-445b-bd15-9820996034ff}">
        <relationship name="audioFile">
            <destination>{c96a8625-306c-4472-bb60-439e701cba23}</destination>
        </relationship>
    </object>
    <object class="SingleSound" id="{4673d664-ecba-4e30-bbe2-3f0326f4b970}">
        <relationship name="audioFile">
            <destination>{96ca080e-cc79-4ee1-9197-fba025ff9ead}</destination>
        </relationship>
    </object>
    <object class="SingleSound" id="{69efb098-63ce-4b37-853c-56c8f463a86e}">
        <relationship name="audioFile">
            <destination>{ce256fd5-2ff1-4672-a347-ce5ab43a02fe}</destination>
        </relationship>
    </object>
    <object class="SingleSound" id="{89ade613-8122-4b41-93d3-8a3db4c9841a}">
        <relationship name="audioFile">
            <destination>{4e9643bb-bbf2-41df-b7a1-f27a769c3a3f}</destination>
        </relationship>
    </object>
    <object class="SingleSound" id="{d3a7cbd3-d24e-4fd6-baa2-ab69f6869696}">
        <relationship name="audioFile">
            <destination>{1a227543-0eb8-4a20-bf16-2c682d5a0c36}</destination>
        </relationship>
    </object>
    <object class="SingleSound" id="{c39a76be-d22d-432c-bbe4-99c039efa272}">
        <relationship name="audioFile">
            <destination>{72e422a5-2d90-4572-a77e-66d8560f336b}</destination>
        </relationship>
    </object>
    <object class="MixerBusEffectChain" id="{85413641-f77c-4e35-b620-5b1eec9f96e1}">
        <relationship name="effects">
            <destination>{064c8dec-a361-4383-b410-7e17997febd4}</destination>
            <destination>{0fe0b7ec-36c1-4a88-945c-432145eef417}</destination>
        </relationship>
    </object>
    <object class="MixerBusPanner" id="{3e19807b-630e-49a9-a46b-f7a0a9edd452}"/>
    <object class="MixerBusFader" id="{0bdff22d-2f0a-4354-927a-663962f5b41e}"/>
    <object class="LimiterEffect" id="{4bab4876-a235-4b22-a8b0-e8c0fc485a1e}">
        <property name="ceiling">
            <value>-2.89999986</value>
        </property>
    </object>
    <object class="LoudnessMeter" id="{9d366cb7-e669-4b78-ae1e-1fdc874a5865}"/>
    <object class="AutomationPoint" id="{fc7271c3-bc1f-4677-b1e2-23b6211487ad}">
        <property name="position">
            <value>0.20000000000000001</value>
        </property>
        <property name="value">
            <value>1</value>
        </property>
        <property name="curveShape">
            <value>0.25471893</value>
        </property>
    </object>
    <object class="AutomationPoint" id="{2d04ce69-498e-4cc3-aca5-a7c850072134}">
        <property name="position">
            <value>0.25</value>
        </property>
        <property name="value">
            <value>0</value>
        </property>
    </object>
    <object class="MixerBusFader" id="{3b26159c-47fa-4ce9-ad2a-45317fa9c99a}"/>
    <object class="ThreeEQEffect" id="{c3f7ee8e-83bf-4a91-835e-635929336d03}">
        <property name="lowGain">
            <value>-5.5</value>
        </property>
        <property name="lowCrossover">
            <value>100</value>
        </property>
        <property name="highCrossover">
            <value>22000</value>
        </property>
        <property name="crossoverSlope">
            <value>0</value>
        </property>
    </object>
    <object class="AutomationPoint" id="{807a6d04-d186-4b28-8f14-5249636e9751}">
        <property name="position">
            <value>0.23000000000000001</value>
        </property>
        <property name="value">
            <value>1</value>
        </property>
        <property name="curveShape">
            <value>0.25471893</value>
        </property>
    </object>
    <object class="AutomationPoint" id="{c882bda8-7808-45c0-84c4-b8dd8df3cabe}">
        <property name="position">
            <value>0.25</value>
        </property>
        <property name="value">
            <value>0</value>
        </property>
    </object>
    <object class="MixerBusFader" id="{d15e0b0f-fb67-4133-9299-1b0cacd72cf2}"/>
    <object class="SFXReverbEffect" id="{057edcb0-847b-4dfc-a184-2192750a60ba}">
        <property name="decayTime">
            <value>150</value>
        </property>
        <property name="earlyDelay">
            <value>10</value>
        </property>
        <property name="lateDelay">
            <value>31</value>
        </property>
        <property name="HFDecayRatio">
            <value>53.5</value>
        </property>
        <property name="diffusion">
            <value>0</value>
        </property>
        <property name="density">
            <value>40</value>
        </property>
        <property name="lowShelfGain">
            <value>-0.5</value>
        </property>
        <property name="highCut">
            <value>7000</value>
        </property>
        <property name="wetLevel">
            <value>-18.5</value>
        </property>
    </object>
    <object class="AutomationPoint" id="{59f60288-e278-4545-a888-ad0bf239b22f}">
        <property name="position">
            <value>0.22</value>
        </property>
        <property name="value">
            <value>1</value>
        </property>
        <property name="curveShape">
            <value>0.25471893</value>
        </property>
    </object>
    <object class="AutomationPoint" id="{fd28e063-9a64-4303-89f7-3fef0115f372}">
        <property name="position">
            <value>0.25</value>
        </property>
        <property name="value">
            <value>0</value>
        </property>
    </object>
    <object class="MixerBusFader" id="{064c8dec-a361-4383-b410-7e17997febd4}"/>
    <object class="ThreeEQEffect" id="{0fe0b7ec-36c1-4a88-945c-432145eef417}">
        <property name="lowGain">
            <value>-20</value>
        </property>
        <property name="highGain">
            <value>6.5</value>
        </property>
        <property name="lowCrossover">
            <value>1200</value>
        </property>
        <property name="highCrossover">
            <value>22000</value>
        </property>
    </object>
</objects>
